ee_extra/Image/__init__.py
ee_extra/Image/basic.py
ee_extra/__init__.py
ee_extra/image/basic.py
ee_extra-0.0.2.dist-info/LICENSE
ee_extra-0.0.2.dist-info/WHEEL
ee_extra-0.0.2.dist-info/METADATA
ee_extra-0.0.2.dist-info/RECORD
