Metadata-Version: 2.1
Name: ee-extra
Version: 0.0.2
Summary: Miscellaneous functions for working with the Earth Engine Python API.
Home-page: https://github.com/r-earthengine/ee_extra
License: Apache Software License 2.0
Author: rgee_team
Author-email: csaybar@gmail.com
Requires-Python: >=3.7,<4.0
Classifier: Development Status :: 3 - Alpha
Classifier: Intended Audience :: Developers
Classifier: License :: Other/Proprietary License
Classifier: Operating System :: OS Independent
Classifier: Programming Language :: Python :: 3
Classifier: Programming Language :: Python :: 3.7
Classifier: Programming Language :: Python :: 3.8
Classifier: Programming Language :: Python :: 3.9
Classifier: Topic :: Software Development :: Libraries :: Python Modules
Requires-Dist: earthengine-api (>=0.1.259,<0.2.0)
Project-URL: Repository, https://github.com/r-earthengine/ee_extra
